conanDefs/Variants.py
conanDefs/__init__.py
reman/ReMan.py
reman/__init__.py
reman-0.2.9.data/scripts/reman
reman-0.2.9.dist-info/METADATA
reman-0.2.9.dist-info/WHEEL
reman-0.2.9.dist-info/top_level.txt
reman-0.2.9.dist-info/RECORD
