Metadata-Version: 2.1
Name: reman
Version: 0.2.9
Summary: ReMan build tools
Classifier: Programming Language :: Python :: 3
Classifier: License :: Other/Proprietary License
Classifier: Operating System :: OS Independent
Requires-Python: >=3.6
Requires-Dist: mariadb
Requires-Dist: aptly-api-client
